{"type":"PR","pr":{"number":142,"head":"c34c6ca246e16fe4000cabb939d0b6b566038b7b"},"user":"CliniqueTandem","status":"draft","branch":"cms/services","collection":"pages","title":"Services offerts","description":"La Clinique Tandem à Laval adopte une approche multidisciplinaire et offre des services de neuropsychologie, psychologie, psychoéducation, thérapie familiale et pédopsychiatrie.","objects":{"entry":{"path":"content/services/_index.md","sha":"f76f9d01dcd9d7c197fcdf39f7e6b818b498e7a5"},"files":[]},"timeStamp":"2017-10-25T04:00:28.877Z"}